src/__init__.py
src/main.py
tests/__init__.py
tests/test_main.py
githubdeployment-2.0.1.dist-info/LICENSE
githubdeployment-2.0.1.dist-info/METADATA
githubdeployment-2.0.1.dist-info/WHEEL
githubdeployment-2.0.1.dist-info/top_level.txt
githubdeployment-2.0.1.dist-info/RECORD
