Metadata-Version: 2.1
Name: githubdeployment
Version: 2.0.1
Summary: Simple tool for auto-deployment
Home-page: https://github.com/komron-m/deployment
Author: Komron Miralizoda
Author-email: miralizoda.komron@gmail.com
License: UNKNOWN
Platform: UNKNOWN
Classifier: Programming Language :: Python :: 3
Classifier: License :: OSI Approved :: MIT License
Classifier: Operating System :: OS Independent
Requires-Python: >=3.6
